{
  "spike": "w16_drawing_acquire",
  "timestamp": "2026-06-05T15:21:30",
  "gates": {
    "drwdot_found": {
      "ok": true,
      "detail": "found 1: ['C:\\\\ProgramData\\\\SOLIDWORKS\\\\SOLIDWORKS 2024\\\\templates\\\\Drawing.DRWDOT']"
    },
    "default_template_string": {
      "ok": false,
      "detail": "value=''"
    },
    "template_available": {
      "ok": true,
      "detail": "using C:\\ProgramData\\SOLIDWORKS\\SOLIDWORKS 2024\\templates\\Drawing.DRWDOT"
    },
    "routeA_newdocument": {
      "ok": true,
      "detail": "type=CDispatch"
    },
    "routeA_qi_idrawingdoc": {
      "ok": true,
      "detail": "type=IDrawingDoc"
    },
    "routeB_newdocument": {
      "ok": true,
      "detail": "type=CDispatch"
    },
    "routeB_dynamic_dispatch": {
      "ok": true,
      "detail": "type=CDispatch"
    },
    "liveness_getsheetnames": {
      "ok": false,
      "detail": "raised: 'tuple' object is not callable"
    },
    "liveness_getfirstview": {
      "ok": false,
      "detail": "raised: (-2147352573, 'Member not found.', None, None)"
    },
    "liveness_getcurrentsheet": {
      "ok": false,
      "detail": "raised: (-2147352573, 'Member not found.', None, None)"
    },
    "liveness_typed_members": {
      "ok": true,
      "detail": "sheets=['Sheet1']"
    },
    "OVERALL_GO": {
      "ok": true,
      "detail": "at least one route acquires IDrawingDoc"
    }
  },
  "routes": {
    "template": {
      "glob_matches": [
        "C:\\ProgramData\\SOLIDWORKS\\SOLIDWORKS 2024\\templates\\Drawing.DRWDOT"
      ],
      "default_template": "",
      "selected": "C:\\ProgramData\\SOLIDWORKS\\SOLIDWORKS 2024\\templates\\Drawing.DRWDOT"
    },
    "A_typed_qi": {
      "status": "NOT_TRIED",
      "newdocument": "OK",
      "doc_type": "CDispatch",
      "gettype_error": "'int' object is not callable",
      "qi_status": "OK"
    },
    "B_late_bind": {
      "status": "NOT_TRIED",
      "newdocument": "OK",
      "dynamic_dispatch": "CDispatch"
    },
    "C_typelib_scan": {
      "status": "NOT_TRIED",
      "error": "(-2147319765, 'Element not found.', None, None)"
    },
    "liveness": {
      "status": "NOT_TRIED",
      "newdocument": "OK",
      "getsheetnames_error": "'tuple' object is not callable",
      "getfirstview_error": "(-2147352573, 'Member not found.', None, None)",
      "getcurrentsheet_error": "(-2147352573, 'Member not found.', None, None)",
      "typed_getsheetnames": [
        "Sheet1"
      ]
    }
  },
  "verdict": "GO"
}