{
  "spec_name": null,
  "feature_count": 10,
  "equation_count": 0,
  "total_mass_mm3": 29777.4,
  "tolerance_mm3": 50.0,
  "features": [
    {
      "name": "SK_Body",
      "actual_mm3": 0.0
    },
    {
      "name": "Extrude_Roller",
      "actual_mm3": 39269.91
    },
    {
      "name": "SK_CentreBore",
      "actual_mm3": 0.0
    },
    {
      "name": "Cut_CentreBore",
      "actual_mm3": -4539.6
    },
    {
      "name": "SK_BearingPocket_NZ",
      "actual_mm3": 0.0
    },
    {
      "name": "Cut_BearingPocket_NZ",
      "actual_mm3": -2287.96
    },
    {
      "name": "SK_BearingPocket_PZ",
      "actual_mm3": 0.0
    },
    {
      "name": "Cut_BearingPocket_PZ",
      "actual_mm3": -2287.96
    },
    {
      "name": "SK_BeltGripGroove",
      "actual_mm3": 0.0
    },
    {
      "name": "Cut_BeltGripGroove",
      "actual_mm3": -376.99
    }
  ]
}
